SEPModules/SEPDecorators.py
SEPModules/SEPIO.py
SEPModules/SEPLogger.py
SEPModules/SEPPrinting.py
SEPModules/SEPUtils.py
SEPModules/__init__.py
SEPModules/_demo/__init__.py
SEPModules/_demo/demo_SEPLogic.py
SEPModules/_test/__init__.py
SEPModules/_test/test_SEPAlgebra.py
SEPModules/_test/test_SEPDecorators.py
SEPModules/_test/test_SEPIO.py
SEPModules/_test/test_SEPLogger.py
SEPModules/_test/test_SEPLogic.py
SEPModules/_test/test_SEPPrinting.py
SEPModules/maths/SEPAlgebra.py
SEPModules/maths/SEPLogic.py
SEPModules/maths/SEPMaths.py
SEPModules/maths/SEPQBF.py
SEPModules/maths/__init__.py
SEPModules-2.2.1.dist-info/METADATA
SEPModules-2.2.1.dist-info/WHEEL
SEPModules-2.2.1.dist-info/top_level.txt
SEPModules-2.2.1.dist-info/RECORD
