Metadata-Version: 2.1
Name: SEPModules
Version: 2.2.1
Summary: SEPModules provides a handful of modules to aid in speeding up the production of small or medium-sized scripts.
Home-page: https://github.com/MarcelSimader/SEPModules
Author: Marcel Simader
Author-email: marcel0simader@gmail.com
License: UNKNOWN
Project-URL: Documentation, https://marcelsimader.github.io/SEPModules/
Project-URL: Source, https://github.com/MarcelSimader/SEPModules
Platform: UNKNOWN
Classifier: Programming Language :: Python :: 3
Classifier: License :: Free for non-commercial use
Classifier: Operating System :: OS Independent
Classifier: Development Status :: 3 - Alpha
Classifier: Environment :: Console
Classifier: Intended Audience :: Developers
Classifier: Topic :: Software Development :: Libraries :: Python Modules
Requires-Python: >=3.6
